netbox_app_systems/__init__.py
netbox_app_systems/filters.py
netbox_app_systems/filtersets.py
netbox_app_systems/forms.py
netbox_app_systems/graphql.py
netbox_app_systems/models.py
netbox_app_systems/navigation.py
netbox_app_systems/tables.py
netbox_app_systems/template_content.py
netbox_app_systems/urls.py
netbox_app_systems/views.py
netbox_app_systems/api/__init__.py
netbox_app_systems/api/serializers.py
netbox_app_systems/api/urls.py
netbox_app_systems/api/views.py
netbox_app_systems/migrations/0001_initial.py
netbox_app_systems/migrations/0002_rename_content_type_appsystemassignment_object_type_and_more.py
netbox_app_systems/migrations/__init__.py
netbox_app_systems/templates/netbox_app_systems/app_system_assignment_edit.html
netbox_app_systems/templates/netbox_app_systems/app_system_panel.html
netbox_app_systems/templates/netbox_app_systems/appsystem.html
netbox_app_systems-0.3.1.dist-info/LICENSE
netbox_app_systems-0.3.1.dist-info/METADATA
netbox_app_systems-0.3.1.dist-info/WHEEL
netbox_app_systems-0.3.1.dist-info/top_level.txt
netbox_app_systems-0.3.1.dist-info/RECORD
